pokernow/__init__.py
pokernow/_version.py
pokernow/exceptions.py
pokernow/pokernow.py
py_pokernow-0.2.0.dist-info/licenses/LICENSE
py_pokernow-0.2.0.dist-info/METADATA
py_pokernow-0.2.0.dist-info/WHEEL
py_pokernow-0.2.0.dist-info/top_level.txt
py_pokernow-0.2.0.dist-info/RECORD
